artificer/cli/__init__.py
artificer/cli/cli.py
artificer/cli/config.py
artificer/cli/feature.py
artificer/cli/loader.py
artificer_cli-0.1.0a6.dist-info/METADATA
artificer_cli-0.1.0a6.dist-info/WHEEL
artificer_cli-0.1.0a6.dist-info/entry_points.txt
artificer_cli-0.1.0a6.dist-info/RECORD
