Metadata-Version: 2.4
Name: artificer-cli
Version: 0.1.0a6
Summary: Shared CLI interface for Artificer — AI dev tooling built on MCP
Author-email: Scott <scott@artificerai.dev>
License: MIT
Keywords: ai,cli,developer-tools,mcp,model-context-protocol
Classifier: Development Status :: 3 - Alpha
Classifier: Environment :: Console
Classifier: Intended Audience :: Developers
Classifier: License :: OSI Approved :: MIT License
Classifier: Operating System :: OS Independent
Classifier: Programming Language :: Python :: 3
Classifier: Programming Language :: Python :: 3.10
Classifier: Programming Language :: Python :: 3.11
Classifier: Programming Language :: Python :: 3.12
Classifier: Programming Language :: Python :: 3.13
Classifier: Topic :: Software Development :: Libraries :: Application Frameworks
Classifier: Typing :: Typed
Requires-Python: >=3.10
Requires-Dist: click>=8.3.1
Requires-Dist: tomli>=2.0.0; python_version < '3.11'
